{
    "year": "1991",
    "month": "10",
    "day": "01",
    "venue": "J.C. Dobbs",
    "city": "Philadelphia",
    "state": "PA",
    "country": "US",
    "band": [
        {
            "members": [
                {
                    "name": "Kurt Cobain",
                    "duty": "vocals, guitar"
                },
                {
                    "name": "Krist Novoselic",
                    "duty": "bass"
                },
                {
                    "name": "Dave Grohl",
                    "duty": "drums, backing vocals"
                }
            ],
            "type": "group",
            "name": "NIRVANA"
        }
    ],
    "crew": [
        {
            "name": "Monty Lee Wilkes",
            "duty": "tour manager & sound engineer"
        },
        {
            "name": "Myles Kennedy",
            "duty": "monitor engineer & drum technician"
        },
        {
            "name": "Nic Close",
            "duty": "guitar technician"
        }
    ],
    "buyer": {
        "names": [
            "Tom Sheehy"
        ]
    },
    "schedule": [
        {
            "event": "Load In",
            "time": null
        },
        {
            "event": "Soundcheck",
            "time": null
        },
        {
            "event": "Doors",
            "time": "19:00"
        },
        {
            "event": "Love Chunks Showtime",
            "time": null
        },
        {
            "event": "Das Damen Showtime",
            "time": null
        },
        {
            "event": "NIRVANA Showtime",
            "time": null
        }
    ],
    "soundcheck": [],
    "soundcheck_incomplete": false,
    "set": [
        {
            "type": "song",
            "text": "Jesus Wants Me For A Sunbeam",
            "notes": []
        },
        {
            "type": "song",
            "text": "Drain You",
            "notes": []
        },
        {
            "type": "song",
            "text": "Aneurysm",
            "notes": []
        },
        {
            "type": "song",
            "text": "Floyd The Barber",
            "notes": []
        },
        {
            "type": "song",
            "text": "Smells Like Teen Spirit",
            "notes": []
        },
        {
            "type": "song",
            "text": "Polly",
            "notes": []
        },
        {
            "type": "song",
            "text": "About A Girl",
            "notes": []
        },
        {
            "type": "song",
            "text": "School",
            "notes": []
        },
        {
            "type": "song",
            "text": "Sliver",
            "notes": []
        },
        {
            "type": "song",
            "text": "Come As You Are",
            "notes": []
        },
        {
            "type": "song",
            "text": "jam",
            "notes": []
        },
        {
            "type": "song",
            "text": "Blew",
            "notes": []
        },
        {
            "type": "song",
            "text": "Been A Son",
            "notes": []
        }
    ],
    "set_incomplete": false,
    "transmission": {},
    "rehearsel_circulating_sources": [],
    "circulating_sources": [
        {
            "name": "AUD #1",
            "complete": true,
            "equipment": "Built in > Unknown",
            "generation": "ANA(M) > FLAC",
            "video-generation": null,
            "audio-generation": null,
            "length-sound": "41 min / 7.0",
            "notes": [
                "In December 2004 the master upgrade was circulated.",
                "\"Jesus Wants Me For A Sunbeam\" cuts in."
            ]
        },
        {
            "name": "AUD #2",
            "complete": true,
            "equipment": "Built in > Realistic SCP-29",
            "generation": "ANA(M) > FLAC",
            "video-generation": null,
            "audio-generation": null,
            "length-sound": "43 min / 8.0",
            "notes": [
                "Circulated in October 2011."
            ]
        }
    ],
    "uncirculated_sources": [
        {
            "name": "SBD #1",
            "note": "The owner of the venue made a point of taping every show there. However, she has reportedly said that she will only make copies if the request comes from the band's record company."
        }
    ],
    "notes": [
        "The band requested extra monitors for the show because Kurt was sick with stomach pains, according to the venue's publicist.",
        "The crowd was unhappy with the band's choice not to play an encore, so they provoked the band with shouts of \"sellouts!\""
    ],
    "press": [],
    "memorabilia": [
        {
            "url": "/concerts/images/1991/1991-10-01/1991-10-01_01.jpg",
            "caption": "Ticket"
        },
        {
            "url": "/concerts/images/1991/1991-10-01/1991-10-01_02.jpg",
            "caption": "Venue events calendar"
        },
        {
            "url": "/concerts/images/1991/1991-10-01/1991-10-01_03.jpg",
            "caption": "Venue event"
        },
        {
            "url": "/concerts/images/1991/1991-10-01/1991-10-01_04.jpg",
            "caption": "Advert"
        }
    ],
    "images": [
        {
            "url": "/concerts/images/1991/1991-10-01/1991-10-01_001.jpg",
            "caption": "Photo by Colonel Tom Sheehy"
        },
        {
            "url": "/concerts/images/1991/1991-10-01/1991-10-01_002.jpg",
            "caption": "Photo by Colonel Tom Sheehy"
        },
        {
            "url": "/concerts/images/1991/1991-10-01/1991-10-01_003.jpg",
            "caption": "Photo by Colonel Tom Sheehy"
        },
        {
            "url": "/concerts/images/1991/1991-10-01/1991-10-01_004.jpg",
            "caption": "Photo by Colonel Tom Sheehy"
        },
        {
            "url": "/concerts/images/1991/1991-10-01/1991-10-01_005.jpg",
            "caption": "Photo by Colonel Tom Sheehy"
        }
    ],
    "navigation": {
        "previous": "91-09-30",
        "next": "91-10-02"
    },
    "graph": {
        "bleach": "4",
        "nevermind": "4",
        "inutero": "0",
        "non": "4"
    }
}