{
    "year": "1993",
    "month": "12",
    "day": "06",
    "venue": "Astroarena",
    "city": "Houston",
    "state": "TX",
    "country": "US",
    "band": [
        {
            "NIRVANA": [
                {
                    "name": "Kurt Cobain ",
                    "duty": "vocals, guitar"
                },
                {
                    "name": "Krist Novoselic ",
                    "duty": "bass"
                },
                {
                    "name": "Dave Grohl ",
                    "duty": "drums, backing vocals"
                },
                {
                    "name": "Pat Smear ",
                    "duty": "guitar"
                },
                {
                    "name": "Lori Goldston ",
                    "duty": "cello"
                }
            ],
            "type": "group"
        }
    ],
    "crew": [
        {
            "name": "Alex MacLeod",
            "duty": "tour manager"
        },
        {
            "name": "Jeff Mason",
            "duty": "production manager"
        },
        {
            "name": "Kelly Nase",
            "duty": "tour accountant"
        },
        {
            "name": "Susanne Sasic",
            "duty": "lighting designer"
        },
        {
            "name": "Craig Overbay",
            "duty": "sound engineer"
        },
        {
            "name": "Ian Beveridge",
            "duty": "monitor engineer"
        },
        {
            "name": "Jim Vincent",
            "duty": "guitar technician"
        },
        {
            "name": "John Duncan",
            "duty": "guitar technician"
        },
        {
            "name": "Earnie Bailey",
            "duty": "guitar technician"
        },
        {
            "name": "Mike Dalke",
            "duty": "drum technician"
        },
        {
            "name": "Ed Swink",
            "duty": "stage manager"
        },
        {
            "name": "Allan Bagley",
            "duty": "Pro Show sound crew"
        },
        {
            "name": "Tom Pfaeffle",
            "duty": "Pro Show sound crew"
        },
        {
            "name": "Niko Vonk",
            "duty": "Pro Show sound crew"
        },
        {
            "name": "Mike Lamb",
            "duty": "LSD lighting crew"
        },
        {
            "name": "Pat Connolly",
            "duty": "LSD lighting crew"
        },
        {
            "name": "Gary Vaspol",
            "duty": "LSD lighting crew"
        }
    ],
    "buyer": {
        "names": [
            "Tom Bunch",
            "Robert Slaughter"
        ],
        "company": "T.A.B. Presents"
    },
    "schedule": [
        {
            "event": "Load In",
            "time": "09:00"
        },
        {
            "event": "Soundcheck",
            "time": "15:30"
        },
        {
            "event": "Doors",
            "time": "18:30"
        },
        {
            "event": "Shonen Knife Showtime",
            "time": "20:00"
        },
        {
            "event": "Breeders Showtime",
            "time": "20:45"
        },
        {
            "event": "NIRVANA Showtime",
            "time": "21:45"
        }
    ],
    "soundcheck": [],
    "soundcheck_incomplete": false,
    "set": [
        {
            "type": "song",
            "text": "Radio Friendly Unit Shifter",
            "notes": []
        },
        {
            "type": "song",
            "text": "Come As You Are",
            "notes": []
        },
        {
            "type": "song",
            "text": "Serve The Servants",
            "notes": []
        },
        {
            "type": "song",
            "text": "Smells Like Teen Spirit",
            "notes": []
        },
        {
            "type": "song",
            "text": "Sliver",
            "notes": []
        },
        {
            "type": "song",
            "text": "Dumb",
            "notes": []
        },
        {
            "type": "song",
            "text": "Pennyroyal Tea",
            "notes": []
        },
        {
            "type": "song",
            "text": "School",
            "notes": []
        },
        {
            "type": "song",
            "text": "Polly",
            "notes": []
        },
        {
            "type": "song",
            "text": "Milk It",
            "notes": []
        },
        {
            "type": "song",
            "text": "Rape Me",
            "notes": []
        },
        {
            "type": "song",
            "text": "Territorial Pissings",
            "notes": []
        },
        {
            "type": "song",
            "text": "Jesus Wants Me For A Sunbeam",
            "notes": []
        },
        {
            "type": "song",
            "text": "All Apologies",
            "notes": []
        },
        {
            "type": "song",
            "text": "Scentless Apprentice",
            "notes": []
        },
        {
            "type": "song",
            "text": "Heart-Shaped Box",
            "notes": []
        },
        {
            "type": "song",
            "text": "Blew",
            "notes": []
        }
    ],
    "set_incomplete": true,
    "transmission": {},
    "rehearsel_circulating_sources": [],
    "circulating_sources": [],
    "uncirculated_sources": [],
    "notes": [
        "According to a newspaper review, Nirvana played for a crowd of about 3,000.",
        "At one point, Krist stopped the show to yell at a guy grabbing a girl's breast, according to an attendee.",
        "In the middle of a noise jam, Kurt reportedly jammed on a bit of \"You Know You're Right.\"",
        "During the encore, Kurt said, \"So, ya'll enjoying your new Pearl Jam record?\"",
        "The show was about 80 minutes long, according to a review."
    ],
    "press": [
        {
            "text": "Review from a USA newspaper called \"Houston Chronicle\", published in 12/08/1993.",
            "url": "/concerts/images/1993/1993-12-06/1993-12-06_01_review.jpg"
        },
        {
            "text": "Review from a USA newspaper called \"Houston Post\", published in December of 1993.",
            "url": "/concerts/images/1993/1993-12-06/1993-12-06_02_review.jpg"
        },
        {
            "text": "Review from a USA newspaper called \"Houston - Public News\", published in 12/08/1993.",
            "url": "/concerts/images/1993/1993-12-06/1993-12-06_03_review.jpg"
        }
    ],
    "memorabilia": [
        {
            "url": "/concerts/images/1993/1993-12-06/1993-12-06_01.jpg",
            "caption": "Handbill/Flyer, designed by Frank Kozik"
        },
        {
            "url": "/concerts/images/1993/1993-12-06/1993-12-06_02.jpg",
            "caption": "Handbill/Flyer, designed by Frank Kozik"
        },
        {
            "url": "/concerts/images/1993/1993-12-06/1993-12-06_03.jpg",
            "caption": "Ticket"
        },
        {
            "url": "/concerts/images/1993/1993-12-06/1993-12-06_04.jpg",
            "caption": "Ticket"
        },
        {
            "url": "/concerts/images/1993/1993-12-06/1993-12-06_05.jpg",
            "caption": "Advert"
        },
        {
            "url": "/concerts/images/1993/1993-12-06/1993-12-06_06.jpg",
            "caption": "Nirvana's tour itinerary"
        }
    ],
    "images": [
        {
            "url": "/concerts/images/1993/1993-12-06/1993-12-06_001.jpg",
            "caption": "Photo by D. Fahleson"
        },
        {
            "url": "/concerts/images/1993/1993-12-06/1993-12-06_002.jpg",
            "caption": "Photo by D. Fahleson"
        },
        {
            "url": "/concerts/images/1993/1993-12-06/1993-12-06_003.jpg",
            "caption": "Photo by D. Fahleson"
        },
        {
            "url": "/concerts/images/1993/1993-12-06/1993-12-06_004.jpg",
            "caption": "Photo by D. Fahleson"
        },
        {
            "url": "/concerts/images/1993/1993-12-06/1993-12-06_005.jpg",
            "caption": "Photo by D. Fahleson"
        },
        {
            "url": "/concerts/images/1993/1993-12-06/1993-12-06_006.jpg",
            "caption": "Photo by D. Fahleson"
        },
        {
            "url": "/concerts/images/1993/1993-12-06/1993-12-06_007.jpg",
            "caption": "Photo by D. Fahleson"
        },
        {
            "url": "/concerts/images/1993/1993-12-06/1993-12-06_008.jpg",
            "caption": "Photo by D. Fahleson"
        },
        {
            "url": "/concerts/images/1993/1993-12-06/1993-12-06_009.jpg",
            "caption": "Photo by D. Fahleson"
        },
        {
            "url": "/concerts/images/1993/1993-12-06/1993-12-06_010.jpg",
            "caption": "Photo by D. Fahleson"
        },
        {
            "url": "/concerts/images/1993/1993-12-06/1993-12-06_011.jpg",
            "caption": "Photo by D. Fahleson"
        },
        {
            "url": "/concerts/images/1993/1993-12-06/1993-12-06_012.jpg",
            "caption": "Photo by D. Fahleson"
        },
        {
            "url": "/concerts/images/1993/1993-12-06/1993-12-06_013.jpg",
            "caption": "Photo by D. Fahleson"
        },
        {
            "url": "/concerts/images/1993/1993-12-06/1993-12-06_014.jpg",
            "caption": "Photo by D. Fahleson"
        },
        {
            "url": "/concerts/images/1993/1993-12-06/1993-12-06_015.jpg",
            "caption": "Photo by D. Fahleson"
        },
        {
            "url": "/concerts/images/1993/1993-12-06/1993-12-06_016.jpg",
            "caption": "Photo by D. Fahleson"
        },
        {
            "url": "/concerts/images/1993/1993-12-06/1993-12-06_017.jpg",
            "caption": "Photo by D. Fahleson"
        },
        {
            "url": "/concerts/images/1993/1993-12-06/1993-12-06_018.jpg",
            "caption": "Photo by D. Fahleson"
        },
        {
            "url": "/concerts/images/1993/1993-12-06/1993-12-06_019.jpg",
            "caption": "Photo by D. Fahleson"
        },
        {
            "url": "/concerts/images/1993/1993-12-06/1993-12-06_020.jpg",
            "caption": "Photo by D. Fahleson"
        },
        {
            "url": "/concerts/images/1993/1993-12-06/1993-12-06_021.jpg",
            "caption": "Photo by D. Fahleson"
        },
        {
            "url": "/concerts/images/1993/1993-12-06/1993-12-06_022.jpg",
            "caption": "Photo by D. Fahleson"
        },
        {
            "url": "/concerts/images/1993/1993-12-06/1993-12-06_023.jpg",
            "caption": "Photo by D. Fahleson"
        },
        {
            "url": "/concerts/images/1993/1993-12-06/1993-12-06_024.jpg",
            "caption": "Photo by D. Fahleson"
        },
        {
            "url": "/concerts/images/1993/1993-12-06/1993-12-06_025.jpg",
            "caption": "Photo by D. Fahleson"
        },
        {
            "url": "/concerts/images/1993/1993-12-06/1993-12-06_026.jpg",
            "caption": "Photo by D. Fahleson"
        },
        {
            "url": "/concerts/images/1993/1993-12-06/1993-12-06_027.jpg",
            "caption": "Photo by D. Fahleson"
        },
        {
            "url": "/concerts/images/1993/1993-12-06/1993-12-06_028.jpg",
            "caption": "Photo by D. Fahleson"
        },
        {
            "url": "/concerts/images/1993/1993-12-06/1993-12-06_029.jpg",
            "caption": "Photo by D. Fahleson"
        },
        {
            "url": "/concerts/images/1993/1993-12-06/1993-12-06_030.jpg",
            "caption": "Photo by Tim Newman"
        }
    ],
    "navigation": {
        "previous": "93-12-05",
        "next": "93-12-08"
    },
    "graph": {
        "bleach": "2",
        "nevermind": "2",
        "inutero": "7",
        "non": "2"
    }
}